pyVS/__init__.py
pyVS/pkg_info.json
pyVS/Test/TestMincIO.py
pyVS/Test/__init__.py
pyVS/Util/FileUtil.py
pyVS/Util/Masker.py
pyVS/Util/StatsUtil.py
pyVS/Util/VoxelOperation.py
pyVS/Util/__init__.py
pyVS/Util/Params/__init__.py
pyVS/Util/Params/pyVSParams.py
pyVS/data/I34.mnc
pyVS/pyVoxelStats/ShareObj.py
pyVS/pyVoxelStats/__init__.py
pyVS/pyVoxelStats/pyVoxelStats.py
pyVS/pyVoxelStats/pyVoxelStatsGAM.py
pyVS/pyVoxelStats/pyVoxelStatsGEE.py
pyVS/pyVoxelStats/pyVoxelStatsGLM.py
pyVS/pyVoxelStats/pyVoxelStatsLM.py
pyVS/pyVoxelStats/pyVoxelStatsPCorr.py
pyVS/pyVoxelStats/pyVoxelStatsPower.py
pyVoxelStats-0.1.6.dist-info/METADATA
pyVoxelStats-0.1.6.dist-info/WHEEL
pyVoxelStats-0.1.6.dist-info/top_level.txt
pyVoxelStats-0.1.6.dist-info/RECORD
