Metadata-Version: 2.1
Name: pyVoxelStats
Version: 0.1.6
Summary: Python implementation of the VoxelStats toolbox for neuroimage analysis
Home-page: http://pypi.python.org/pypi/pyVoxelStats_v016/
Author: Sulantha Mathotaarachchi
Author-email: sulantha.ms@gmail.com
License: UNKNOWN
Platform: UNKNOWN
Requires-Dist: nibabel
Requires-Dist: pandas
Requires-Dist: numpy
Requires-Dist: scipy
Requires-Dist: numexpr
Requires-Dist: pyminc
Requires-Dist: statsmodels
Requires-Dist: rpy2
Requires-Dist: ipyparallel
